insert_mongodb/__init__.py
insert_mongodb-0.1.0.dist-info/METADATA
insert_mongodb-0.1.0.dist-info/WHEEL
insert_mongodb-0.1.0.dist-info/top_level.txt
insert_mongodb-0.1.0.dist-info/RECORD
