Metadata-Version: 2.1
Name: insert-mongodb
Version: 0.1.0
Summary: 将json导入mongodb
Home-page: https://github.com/zyzlaozhang/insert_mongodb
Author: zyzlaozhang2011
Author-email: zyzlaozhang2011@163.com
License: MIT
Classifier: License :: OSI Approved :: MIT License
Classifier: Programming Language :: Python
Classifier: Programming Language :: Python :: 3
Classifier: Programming Language :: Python :: 3.6
Classifier: Programming Language :: Python :: Implementation :: CPython
Classifier: Programming Language :: Python :: Implementation :: PyPy
Requires-Python: >=3.6.0
